calcula/__init__.py
calcula/calcula.py
calcula-0.0.1.dist-info/METADATA
calcula-0.0.1.dist-info/WHEEL
calcula-0.0.1.dist-info/entry_points.txt
calcula-0.0.1.dist-info/top_level.txt
calcula-0.0.1.dist-info/RECORD
