Metadata-Version: 2.1
Name: calcula
Version: 0.0.1
Summary: Uma calculadora simples que suporta operações básicas em Python.
Home-page: https://github.com/elvingup/calcula-01.git
Author: elvingup
Author-email: el.cayro@gmail.com
Classifier: Programming Language :: Python :: 3
Classifier: License :: OSI Approved :: MIT License
Classifier: Operating System :: OS Independent
Requires-Python: >=3.6
